ppxf_assistant/__init__.py
ppxf_assistant/ppxf_assistant.py
ppxf_assistant-0.0.4.dist-info/LICENSE
ppxf_assistant-0.0.4.dist-info/METADATA
ppxf_assistant-0.0.4.dist-info/WHEEL
ppxf_assistant-0.0.4.dist-info/top_level.txt
ppxf_assistant-0.0.4.dist-info/RECORD
