Metadata-Version: 2.1
Name: ppxf-assistant
Version: 0.0.4
Summary: A small package that can make using PPxF easier, specially for integrated field spectra.
Home-page: UNKNOWN
Author: Diego Gonzalez
Author-email: djgh.117@gmail.com
License: UNKNOWN
Platform: UNKNOWN
Classifier: Programming Language :: Python :: 3
Classifier: License :: OSI Approved :: MIT License
Classifier: Operating System :: OS Independent
Requires-Python: >=3.6
Requires-Dist: numpy
Requires-Dist: matplotlib
Requires-Dist: astropy
Requires-Dist: panel
Requires-Dist: ppxf
